coloro/__init__.py
coloro/main.py
coloro-0.0.2.dist-info/LICENSE.txt
coloro-0.0.2.dist-info/METADATA
coloro-0.0.2.dist-info/WHEEL
coloro-0.0.2.dist-info/entry_points.txt
coloro-0.0.2.dist-info/top_level.txt
coloro-0.0.2.dist-info/RECORD
