Metadata-Version: 2.1
Name: coloro
Version: 0.0.2
Summary: A console tool for output text with highlighted hex colors
Home-page: https://github.com/Insolita/coloro
Author: Insolita
Author-email: webmaster100500@ya.ru
License: MIT
Download-URL: https://github.com/Insolita/coloro/tarball/master
Keywords: terminal,color,term_color,clipboard,console
Platform: UNKNOWN
Classifier: Programming Language :: Python :: 3
Classifier: License :: OSI Approved :: MIT License
Requires-Python: >=3.4
Requires-Dist: clipboard (>=0.0.3)
